[{"occupation": "composer", "retrieved": {"male": 43, "unknown": 45, "andy": 4, "female": 6, "mostly_female": 1, "mostly_male": 1}, "ground_truth": {"m": 78, "u": 3, "f": 1}}, {"occupation": "figure", "retrieved": {"unknown": 95, "female": 4, "male": 1, "mostly_male": 0, "mostly_female": 0}, "ground_truth": {"m": 22, "f": 4, "u": 1}}, {"occupation": "artist", "retrieved": {"male": 16, "unknown": 77, "female": 6, "mostly_female": 1, "mostly_male": 0}, "ground_truth": {"m": 77, "f": 4, "u": 1}}, {"occupation": "musician", "retrieved": {"male": 56, "unknown": 38, "female": 3, "mostly_male": 1, "andy": 2, "mostly_female": 0}, "ground_truth": {"m": 7, "f": 2}}, {"occupation": "architect", "retrieved": {"unknown": 59, "male": 41, "mostly_male": 0, "female": 0, "mostly_female": 0}, "ground_truth": {"f": 1, "m": 5}}]